awaitlet/__init__.py
awaitlet/base.py
awaitlet/util/__init__.py
awaitlet/util/testing.py
awaitlet/util/typing.py
docs/api.html
docs/changelog.html
docs/genindex.html
docs/index.html
docs/search.html
docs/searchindex.js
docs/sqlalchemy.html
docs/synopsis.html
docs/_sources/api.rst.txt
docs/_sources/changelog.rst.txt
docs/_sources/index.rst.txt
docs/_sources/sqlalchemy.rst.txt
docs/_sources/synopsis.rst.txt
docs/_static/basic.css
docs/_static/changelog.css
docs/_static/clipboard.min.js
docs/_static/copybutton.css
docs/_static/copybutton.js
docs/_static/copybutton_funcs.js
docs/_static/doctools.js
docs/_static/documentation_options.js
docs/_static/file.png
docs/_static/language_data.js
docs/_static/minus.png
docs/_static/nature.css
docs/_static/nature_override.css
docs/_static/plus.png
docs/_static/pygments.css
docs/_static/searchtools.js
docs/_static/site_custom_css.css
docs/_static/sphinx_highlight.js
docs/_static/sphinx_paramlinks.css
docs/build/Makefile
docs/build/api.rst
docs/build/builder.py
docs/build/changelog.rst
docs/build/conf.py
docs/build/index.rst
docs/build/requirements.txt
docs/build/sqlalchemy.rst
docs/build/synopsis.rst
docs/build/_static/nature_override.css
docs/build/_static/site_custom_css.css
docs/build/_templates/site_custom_sidebars.html
docs/build/unreleased/README.txt
tests/__init__.py
tests/conftest.py
tests/test_concurrency.py
tests/test_sqlalchemy.py
awaitlet-0.0.1.dist-info/LICENSE
awaitlet-0.0.1.dist-info/METADATA
awaitlet-0.0.1.dist-info/WHEEL
awaitlet-0.0.1.dist-info/top_level.txt
awaitlet-0.0.1.dist-info/RECORD
