Metadata-Version: 2.1
Name: awaitlet
Version: 0.0.1
Summary: Allow non-async defs that invoke awaitables inside of asyncio applications
Author-email: Mike Bayer <mike_mp@zzzcomputing.com>
License: Copyright 2024 Michael Bayer
Project-URL: Homepage, https://github.com/sqlalchemy/awaitlet
Project-URL: Documentation, https://awaitlet.sqlalchemy.org
Keywords: asyncio
Classifier: Development Status :: 4 - Beta
Classifier: Intended Audience :: Developers
Classifier: License :: OSI Approved :: MIT License
Classifier: Programming Language :: Python
Classifier: Programming Language :: Python :: 3
Classifier: Operating System :: OS Independent
Requires-Python: >=3.8
License-File: LICENSE
Requires-Dist: greenlet >=1
Requires-Dist: typing-extensions >=4.6.0
